esparto/__init__.py
esparto/__main__.py
esparto/_cli.py
esparto/_options.py
esparto/design/__init__.py
esparto/design/adaptors.py
esparto/design/base.py
esparto/design/content.py
esparto/design/layout.py
esparto/publish/__init__.py
esparto/publish/contentdeps.py
esparto/publish/output.py
esparto/resources/css/bootstrap.min.css
esparto/resources/css/esparto.css
esparto/resources/jinja/base.html.jinja
esparto/resources/js/esparto.js
esparto-4.3.1.dist-info/LICENSE
esparto-4.3.1.dist-info/METADATA
esparto-4.3.1.dist-info/WHEEL
esparto-4.3.1.dist-info/RECORD
