Metadata-Version: 2.1
Name: esparto
Version: 4.3.1
Summary: Data driven report builder for the PyData ecosystem.
Home-page: https://domvwt.github.io/esparto
License: MIT
Author: Dominic Thorn
Author-email: dominic.thorn@gmail.com
Requires-Python: >=3.6.1
Classifier: Development Status :: 5 - Production/Stable
Classifier: Intended Audience :: Developers
Classifier: License :: OSI Approved :: MIT License
Classifier: Programming Language :: Python :: 3
Classifier: Programming Language :: Python :: 3.7
Classifier: Programming Language :: Python :: 3.8
Classifier: Programming Language :: Python :: 3.9
Classifier: Programming Language :: Python :: 3.10
Classifier: Programming Language :: Python :: 3.11
Classifier: Programming Language :: Python :: 3.10
Classifier: Programming Language :: Python :: 3.11
Classifier: Programming Language :: Python :: 3.6
Classifier: Programming Language :: Python :: 3.7
Classifier: Programming Language :: Python :: 3.8
Classifier: Programming Language :: Python :: 3.9
Provides-Extra: extras
Requires-Dist: beautifulsoup4 (>=4.7)
Requires-Dist: dataclasses ; python_version < "3.7"
Requires-Dist: jinja2 (>=2.10.1)
Requires-Dist: markdown (>=3.1)
Requires-Dist: pyyaml (>=5.1)
Requires-Dist: weasyprint (>=51) ; extra == "extras"
Project-URL: Repository, https://github.com/domvwt/esparto
